encode_decode/__init__.py
encode_decode/encoder_decoder.py
encode_decode_shahed-0.1.0.dist-info/LICENSE
encode_decode_shahed-0.1.0.dist-info/METADATA
encode_decode_shahed-0.1.0.dist-info/WHEEL
encode_decode_shahed-0.1.0.dist-info/top_level.txt
encode_decode_shahed-0.1.0.dist-info/RECORD
