Metadata-Version: 2.2
Name: encode-decode-shahed
Version: 0.1.0
Summary: A simple encoding and decoding package
Home-page: https://github.com/shahedltd/encode_decode
Author: MD Shahed Rahman
Author-email: shahedrahmanltd@gmail.com
Classifier: Programming Language :: Python :: 3
Classifier: License :: OSI Approved :: MIT License
Classifier: Operating System :: OS Independent
Requires-Python: >=3.6
License-File: LICENSE
Dynamic: author
Dynamic: author-email
Dynamic: classifier
Dynamic: description-content-type
Dynamic: home-page
Dynamic: requires-python
Dynamic: summary
